{"stats":{"minecraft:custom":{"minecraft:jump":179,"minecraft:time_since_rest":5031,"minecraft:damage_taken":100,"minecraft:crouch_one_cm":49,"minecraft:leave_game":3,"minecraft:play_time":5031,"minecraft:sprint_one_cm":8653,"minecraft:time_since_death":5031,"minecraft:walk_on_water_one_cm":419,"minecraft:walk_one_cm":2785,"minecraft:sneak_time":50,"minecraft:total_world_time":5340,"minecraft:walk_under_water_one_cm":7503,"minecraft:fall_one_cm":4860,"minecraft:fly_one_cm":108541},"minecraft:used":{"ocalotus_originals_edition:itemseapurslane":3,"ocalotus_originals_edition:sea_purslanelayover":14,"minecraft:sweet_berries":1}},"DataVersion":3120}